BeeDrive/__init__.py
BeeDrive/__main__.py
BeeDrive/app.py
BeeDrive/client.py
BeeDrive/cloud.py
BeeDrive/configures.py
BeeDrive/proxy.py
BeeDrive/core/Client.py
BeeDrive/core/Proxy.py
BeeDrive/core/Server.py
BeeDrive/core/__init__.py
BeeDrive/core/browser.py
BeeDrive/core/constant.py
BeeDrive/core/crypto.py
BeeDrive/core/downloader.py
BeeDrive/core/encrypt.py
BeeDrive/core/logger.py
BeeDrive/core/uploader.py
BeeDrive/core/utils.py
BeeDrive/core/base/__init__.py
BeeDrive/core/base/client.py
BeeDrive/core/base/idcard.py
BeeDrive/core/base/manager.py
BeeDrive/core/base/server.py
BeeDrive/core/base/waiter.py
BeeDrive/core/base/worker.py
BeeDrive/lib/Client.py
BeeDrive/lib/Proxy.py
BeeDrive/lib/Server.py
BeeDrive/lib/__init__.py
BeeDrive/lib/browser.py
BeeDrive/lib/commander.py
BeeDrive/lib/constant.py
BeeDrive/lib/downloader.py
BeeDrive/lib/encrypt.py
BeeDrive/lib/logger.py
BeeDrive/lib/uploader.py
BeeDrive/lib/utils.py
BeeDrive/lib/core/__init__.py
BeeDrive/lib/core/client.py
BeeDrive/lib/core/idcard.py
BeeDrive/lib/core/locker.py
BeeDrive/lib/core/manager.py
BeeDrive/lib/core/server.py
BeeDrive/lib/core/utils.py
BeeDrive/lib/core/waiter.py
BeeDrive/lib/core/worker.py
BeeDrive/source/icon.ico
BeeDrive/source/icon.png
BeeDrive/source/index.html
BeeDrive-0.4.0.0.dist-info/METADATA
BeeDrive-0.4.0.0.dist-info/WHEEL
BeeDrive-0.4.0.0.dist-info/entry_points.txt
BeeDrive-0.4.0.0.dist-info/top_level.txt
BeeDrive-0.4.0.0.dist-info/RECORD
