Metadata-Version: 2.1
Name: BeeDrive
Version: 0.4.0.0
Summary: BeeDrive: Open Source Privacy File Transfering System for Teams and Individual Developers
Home-page: https://github.com/JacksonWuxs/BeeDrive
Author: Xuansheng Wu
Maintainer: Xuansheng Wu
License: GPL v3
Platform: all
Classifier: License :: OSI Approved :: GNU General Public License v3 (GPLv3)
Classifier: Programming Language :: Python :: 3
Classifier: Operating System :: MacOS :: MacOS X
Classifier: Operating System :: Microsoft :: Windows
Classifier: Operating System :: POSIX
Requires-Python: >=3
Requires-Dist: pycryptodome
Requires-Dist: PySimpleGUI
Requires-Dist: qrcode
